psql2bigquery/__init__.py
psql2bigquery/main.py
psql2bigquery/run.py
psql2bigquery/tools/__init__.py
psql2bigquery/tools/bigquery.py
psql2bigquery/tools/config.py
psql2bigquery/tools/logging.py
psql2bigquery/tools/psql.py
psql2bigquery-0.0.3.dist-info/entry_points.txt
psql2bigquery-0.0.3.dist-info/WHEEL
psql2bigquery-0.0.3.dist-info/METADATA
psql2bigquery-0.0.3.dist-info/RECORD
